.gitignore
LICENSE
Makefile
README.md
config-sourmash.toml
config-test.toml
requirements.txt
ribbity-test.dmp
setup.cfg
setup.py
site-config.toml
.github/workflows/test.yml
output_docs/config-alt.toml
output_docs/config-test.toml
output_docs/alt-test-site/1-test-issue-number-1.md
output_docs/alt-test-site/3-test-toml-config.md
output_docs/alt-test-site/6-test-other-things.md
output_docs/alt-test-site/7-issue-with-labels.md
output_docs/alt-test-site/8-what-happens-with-external-links.md
output_docs/alt-test-site/9-this-issue-refers-to-another-issue.md
output_docs/alt-test-site/a-page.md
output_docs/alt-test-site/examples.md
output_docs/alt-test-site/index.md
output_docs/alt-test-site/l-duplicate.md
output_docs/alt-test-site/l-good first issue.md
output_docs/alt-test-site/labels.md
output_docs/test-site/1-test-issue-number-1.md
output_docs/test-site/3-test-toml-config.md
output_docs/test-site/6-test-other-things.md
output_docs/test-site/7-issue-with-labels.md
output_docs/test-site/8-what-happens-with-external-links.md
output_docs/test-site/9-this-issue-refers-to-another-issue.md
output_docs/test-site/a-page.md
output_docs/test-site/examples.md
output_docs/test-site/index.md
output_docs/test-site/l-duplicate.md
output_docs/test-site/l-good first issue.md
output_docs/test-site/labels.md
ribbity/__init__.py
ribbity/__main__.py
ribbity/config.py
ribbity/main_build.py
ribbity/main_pull.py
ribbity/objects.py
ribbity/parse_md.py
ribbity/render.py
ribbity/version.py
ribbity.egg-info/PKG-INFO
ribbity.egg-info/SOURCES.txt
ribbity.egg-info/dependency_links.txt
ribbity.egg-info/entry_points.txt
ribbity.egg-info/requires.txt
ribbity.egg-info/top_level.txt
ribbity/templates/_generic_issue.md
ribbity/templates/_generic_label.md
ribbity/templates/examples.md
ribbity/templates/index.md
ribbity/templates/labels.md
site-templates/index.md
tests/test_alt_site_config.py
tests/test_basic.py
tests/test_config.py
tests/test-files/config-test-1.toml
tests/test-files/config-test-alt-site.toml
tests/test-files/site-templates.test/a-page.md