Metadata-Version: 2.1
Name: ribbity
Version: 0.4.1
Summary: convert github issues into a mkdocs site
Home-page: https://github.com/ctb/ribbity
Author: C. Titus Brown
Author-email: titus@idyll.org
License: BSD 3-clause
Platform: UNKNOWN
Classifier: Environment :: Console
Classifier: Environment :: MacOS X
Classifier: Intended Audience :: Science/Research
Classifier: License :: OSI Approved :: BSD License
Classifier: Natural Language :: English
Classifier: Operating System :: POSIX :: Linux
Classifier: Operating System :: MacOS :: MacOS X
Classifier: Programming Language :: Python :: 3.7
Classifier: Programming Language :: Python :: 3.8
Classifier: Programming Language :: Python :: 3.9
License-File: LICENSE
